gohumanloop/__init__.py
gohumanloop/__main__.py
gohumanloop/adapters/__init__.py
gohumanloop/adapters/base_adapter.py
gohumanloop/adapters/langgraph_adapter.py
gohumanloop/cli/__init__.py
gohumanloop/cli/main.py
gohumanloop/core/__init__.py
gohumanloop/core/interface.py
gohumanloop/core/manager.py
gohumanloop/manager/__init__.py
gohumanloop/manager/ghl_manager.py
gohumanloop/models/__init__.py
gohumanloop/models/api_model.py
gohumanloop/models/glh_model.py
gohumanloop/providers/__init__.py
gohumanloop/providers/api_provider.py
gohumanloop/providers/base.py
gohumanloop/providers/email_provider.py
gohumanloop/providers/ghl_provider.py
gohumanloop/providers/terminal_provider.py
gohumanloop/utils/__init__.py
gohumanloop/utils/context_formatter.py
gohumanloop/utils/threadsafedict.py
gohumanloop/utils/utils.py
gohumanloop-0.0.15.dist-info/licenses/LICENSE
gohumanloop-0.0.15.dist-info/METADATA
gohumanloop-0.0.15.dist-info/WHEEL
gohumanloop-0.0.15.dist-info/entry_points.txt
gohumanloop-0.0.15.dist-info/top_level.txt
gohumanloop-0.0.15.dist-info/RECORD
