Metadata-Version: 2.4
Name: gohumanloop
Version: 0.0.15
Summary: Perfecting AI workflows with human intelligence
Author-email: gohumanloop authors <baird0917@163.com>
Project-URL: repository, https://github.com/ptonlix/gohumanloop
Requires-Python: >=3.10
License-File: LICENSE
Requires-Dist: aiohttp>=3.11.16
Requires-Dist: click>=8.1.8
Requires-Dist: dotenv>=0.9.9
Requires-Dist: pydantic>=2.11.3
Requires-Dist: tomli>=2.2.1
Provides-Extra: email
Requires-Dist: imapclient>=3.0.1; extra == "email"
Provides-Extra: langgraph
Requires-Dist: langgraph>=0.3.30; extra == "langgraph"
Provides-Extra: apiservices
Requires-Dist: fastapi>=0.115.12; extra == "apiservices"
Requires-Dist: uvicorn>=0.34.2; extra == "apiservices"
Provides-Extra: agentops
Requires-Dist: agentops>=0.4.12; extra == "agentops"
Dynamic: license-file
